{
    "turns": [
        {
            "guess": "5,5\n", 
            "elapsed": 0.015282869338989258, 
            "turnnum": 1, 
            "notify": "5,5\n", 
            "starttime": 1437124407.358046, 
            "active": 0, 
            "response": "M"
        }, 
        {
            "guess": "7,6\n", 
            "elapsed": 0.025846004486083984, 
            "turnnum": 2, 
            "notify": "7,6\n", 
            "starttime": 1437124407.373345, 
            "active": 1, 
            "response": "M"
        }, 
        {
            "guess": "7,3\n", 
            "elapsed": 0.0221560001373291, 
            "turnnum": 3, 
            "notify": "7,3\n", 
            "starttime": 1437124407.399207, 
            "active": 0, 
            "response": "M"
        }, 
        {
            "guess": "2,5\n", 
            "elapsed": 0.04828906059265137, 
            "turnnum": 4, 
            "notify": "2,5\n", 
            "starttime": 1437124407.421377, 
            "active": 1, 
            "response": "H"
        }, 
        {
            "guess": "4,2\n", 
            "elapsed": 0.03375601768493652, 
            "turnnum": 5, 
            "notify": "4,2\n", 
            "starttime": 1437124407.469683, 
            "active": 0, 
            "response": "M"
        }, 
        {
            "guess": "1,5\n", 
            "elapsed": 0.014472007751464844, 
            "turnnum": 6, 
            "notify": "1,5\n", 
            "starttime": 1437124407.503453, 
            "active": 1, 
            "response": "M"
        }, 
        {
            "guess": "5,7\n", 
            "elapsed": 0.018776893615722656, 
            "turnnum": 7, 
            "notify": "5,7\n", 
            "starttime": 1437124407.517936, 
            "active": 0, 
            "response": "M"
        }, 
        {
            "guess": "2,6\n", 
            "elapsed": 0.023005962371826172, 
            "turnnum": 8, 
            "notify": "2,6\n", 
            "starttime": 1437124407.536729, 
            "active": 1, 
            "response": "M"
        }, 
        {
            "guess": "3,7\n", 
            "elapsed": 0.008903980255126953, 
            "turnnum": 9, 
            "notify": "3,7\n", 
            "starttime": 1437124407.559746, 
            "active": 0, 
            "response": "M"
        }, 
        {
            "guess": "2,4\n", 
            "elapsed": 0.03393387794494629, 
            "turnnum": 10, 
            "notify": "2,4\n", 
            "starttime": 1437124407.568664, 
            "active": 1, 
            "response": "H"
        }, 
        {
            "guess": "2,4\n", 
            "elapsed": 0.01028299331665039, 
            "turnnum": 11, 
            "notify": "2,4\n", 
            "starttime": 1437124407.602608, 
            "active": 0, 
            "response": "M"
        }, 
        {
            "guess": "1,4\n", 
            "elapsed": 0.03310894966125488, 
            "turnnum": 12, 
            "notify": "1,4\n", 
            "starttime": 1437124407.612903, 
            "active": 1, 
            "response": "M"
        }, 
        {
            "guess": "7,7\n", 
            "elapsed": 0.00580596923828125, 
            "turnnum": 13, 
            "notify": "7,7\n", 
            "starttime": 1437124407.646025, 
            "active": 0, 
            "response": "M"
        }, 
        {
            "guess": "2,3\n", 
            "elapsed": 0.03675103187561035, 
            "turnnum": 14, 
            "notify": "2,3\n", 
            "starttime": 1437124407.651843, 
            "active": 1, 
            "response": "H"
        }, 
        {
            "guess": "7,5\n", 
            "elapsed": 0.003720998764038086, 
            "turnnum": 15, 
            "notify": "7,5\n", 
            "starttime": 1437124407.688605, 
            "active": 0, 
            "response": "M"
        }, 
        {
            "guess": "1,3\n", 
            "elapsed": 0.0362548828125, 
            "turnnum": 16, 
            "notify": "1,3\n", 
            "starttime": 1437124407.692336, 
            "active": 1, 
            "response": "M"
        }, 
        {
            "guess": "2,2\n", 
            "elapsed": 0.0076100826263427734, 
            "turnnum": 17, 
            "notify": "2,2\n", 
            "starttime": 1437124407.728601, 
            "active": 0, 
            "response": "M"
        }, 
        {
            "guess": "2,2\n", 
            "elapsed": 0.03445005416870117, 
            "turnnum": 18, 
            "notify": "2,2\n", 
            "starttime": 1437124407.736223, 
            "active": 1, 
            "response": "SB"
        }, 
        {
            "guess": "5,3\n", 
            "elapsed": 0.010805845260620117, 
            "turnnum": 19, 
            "notify": "5,3\n", 
            "starttime": 1437124407.770683, 
            "active": 0, 
            "response": "M"
        }, 
        {
            "guess": "3,3\n", 
            "elapsed": 0.03510904312133789, 
            "turnnum": 20, 
            "notify": "3,3\n", 
            "starttime": 1437124407.781502, 
            "active": 1, 
            "response": "M"
        }, 
        {
            "guess": "2,6\n", 
            "elapsed": 0.0040090084075927734, 
            "turnnum": 21, 
            "notify": "2,6\n", 
            "starttime": 1437124407.816622, 
            "active": 0, 
            "response": "M"
        }, 
        {
            "guess": "3,2\n", 
            "elapsed": 0.04198098182678223, 
            "turnnum": 22, 
            "notify": "3,2\n", 
            "starttime": 1437124407.820641, 
            "active": 1, 
            "response": "M"
        }, 
        {
            "guess": "4,4\n", 
            "elapsed": 0.004386186599731445, 
            "turnnum": 23, 
            "notify": "4,4\n", 
            "starttime": 1437124407.862635, 
            "active": 0, 
            "response": "H"
        }, 
        {
            "guess": "3,5\n", 
            "elapsed": 0.044196128845214844, 
            "turnnum": 24, 
            "notify": "3,5\n", 
            "starttime": 1437124407.867029, 
            "active": 1, 
            "response": "H"
        }, 
        {
            "guess": "3,4\n", 
            "elapsed": 0.005881071090698242, 
            "turnnum": 25, 
            "notify": "3,4\n", 
            "starttime": 1437124407.911233, 
            "active": 0, 
            "response": "M"
        }, 
        {
            "guess": "4,5\n", 
            "elapsed": 0.03885507583618164, 
            "turnnum": 26, 
            "notify": "4,5\n", 
            "starttime": 1437124407.917125, 
            "active": 1, 
            "response": "H"
        }, 
        {
            "guess": "4,5\n", 
            "elapsed": 0.006871938705444336, 
            "turnnum": 27, 
            "notify": "4,5\n", 
            "starttime": 1437124407.956002, 
            "active": 0, 
            "response": "H"
        }, 
        {
            "guess": "4,4\n", 
            "elapsed": 0.03582119941711426, 
            "turnnum": 28, 
            "notify": "4,4\n", 
            "starttime": 1437124407.96289, 
            "active": 1, 
            "response": "M"
        }, 
        {
            "guess": "4,3\n", 
            "elapsed": 0.006304025650024414, 
            "turnnum": 29, 
            "notify": "4,3\n", 
            "starttime": 1437124407.998724, 
            "active": 0, 
            "response": "M"
        }, 
        {
            "guess": "1,2\n", 
            "elapsed": 0.039320945739746094, 
            "turnnum": 30, 
            "notify": "1,2\n", 
            "starttime": 1437124408.005037, 
            "active": 1, 
            "response": "M"
        }, 
        {
            "guess": "4,6\n", 
            "elapsed": 0.004427194595336914, 
            "turnnum": 31, 
            "notify": "4,6\n", 
            "starttime": 1437124408.044371, 
            "active": 0, 
            "response": "H"
        }, 
        {
            "guess": "3,6\n", 
            "elapsed": 0.03764200210571289, 
            "turnnum": 32, 
            "notify": "3,6\n", 
            "starttime": 1437124408.048804, 
            "active": 1, 
            "response": "M"
        }, 
        {
            "guess": "4,7\n", 
            "elapsed": 0.007648944854736328, 
            "turnnum": 33, 
            "notify": "4,7\n", 
            "starttime": 1437124408.086457, 
            "active": 0, 
            "response": "SB"
        }, 
        {
            "guess": "3,4\n", 
            "elapsed": 0.035368919372558594, 
            "turnnum": 34, 
            "notify": "3,4\n", 
            "starttime": 1437124408.094115, 
            "active": 1, 
            "response": "M"
        }, 
        {
            "guess": "4,8\n", 
            "elapsed": 0.007916927337646484, 
            "turnnum": 35, 
            "notify": "4,8\n", 
            "starttime": 1437124408.129496, 
            "active": 0, 
            "response": "M"
        }, 
        {
            "guess": "3,4\n", 
            "elapsed": 0.038815975189208984, 
            "turnnum": 36, 
            "notify": "3,4\n", 
            "starttime": 1437124408.137425, 
            "active": 1, 
            "response": "M"
        }, 
        {
            "guess": "6,2\n", 
            "elapsed": 0.00849008560180664, 
            "turnnum": 37, 
            "notify": "6,2\n", 
            "starttime": 1437124408.176262, 
            "active": 0, 
            "response": "H"
        }, 
        {
            "guess": "4,6\n", 
            "elapsed": 0.034433841705322266, 
            "turnnum": 38, 
            "notify": "4,6\n", 
            "starttime": 1437124408.18476, 
            "active": 1, 
            "response": "M"
        }, 
        {
            "guess": "7,2\n", 
            "elapsed": 0.00967097282409668, 
            "turnnum": 39, 
            "notify": "7,2\n", 
            "starttime": 1437124408.219211, 
            "active": 0, 
            "response": "M"
        }, 
        {
            "guess": "2,1\n", 
            "elapsed": 0.03588294982910156, 
            "turnnum": 40, 
            "notify": "2,1\n", 
            "starttime": 1437124408.22889, 
            "active": 1, 
            "response": "M"
        }, 
        {
            "guess": "6,3\n", 
            "elapsed": 0.008640050888061523, 
            "turnnum": 41, 
            "notify": "6,3\n", 
            "starttime": 1437124408.264788, 
            "active": 0, 
            "response": "H"
        }, 
        {
            "guess": "5,5\n", 
            "elapsed": 0.039273977279663086, 
            "turnnum": 42, 
            "notify": "5,5\n", 
            "starttime": 1437124408.273443, 
            "active": 1, 
            "response": "SD"
        }, 
        {
            "guess": "6,1\n", 
            "elapsed": 0.004846096038818359, 
            "turnnum": 43, 
            "notify": "6,1\n", 
            "starttime": 1437124408.312727, 
            "active": 0, 
            "response": "M"
        }, 
        {
            "guess": "5,4\n", 
            "elapsed": 0.044332027435302734, 
            "turnnum": 44, 
            "notify": "5,4\n", 
            "starttime": 1437124408.317582, 
            "active": 1, 
            "response": "M"
        }, 
        {
            "guess": "6,4\n", 
            "elapsed": 0.0032508373260498047, 
            "turnnum": 45, 
            "notify": "6,4\n", 
            "starttime": 1437124408.361926, 
            "active": 0, 
            "response": "SD"
        }, 
        {
            "guess": "6,5\n", 
            "elapsed": 0.042327165603637695, 
            "turnnum": 46, 
            "notify": "6,5\n", 
            "starttime": 1437124408.365188, 
            "active": 1, 
            "response": "H"
        }, 
        {
            "guess": "6,5\n", 
            "elapsed": 0.004500865936279297, 
            "turnnum": 47, 
            "notify": "6,5\n", 
            "starttime": 1437124408.407529, 
            "active": 0, 
            "response": "M"
        }, 
        {
            "guess": "7,5\n", 
            "elapsed": 0.03929901123046875, 
            "turnnum": 48, 
            "notify": "7,5\n", 
            "starttime": 1437124408.412042, 
            "active": 1, 
            "response": "M"
        }, 
        {
            "guess": "1,9\n", 
            "elapsed": 0.007961034774780273, 
            "turnnum": 49, 
            "notify": "1,9\n", 
            "starttime": 1437124408.451355, 
            "active": 0, 
            "response": "M"
        }, 
        {
            "guess": "6,6\n", 
            "elapsed": 0.03821992874145508, 
            "turnnum": 50, 
            "notify": "6,6\n", 
            "starttime": 1437124408.459327, 
            "active": 1, 
            "response": "H"
        }, 
        {
            "guess": "9,1\n", 
            "elapsed": 0.010983943939208984, 
            "turnnum": 51, 
            "notify": "9,1\n", 
            "starttime": 1437124408.497565, 
            "active": 0, 
            "response": "M"
        }, 
        {
            "guess": "5,6\n", 
            "elapsed": 0.030400991439819336, 
            "turnnum": 52, 
            "notify": "5,6\n", 
            "starttime": 1437124408.508559, 
            "active": 1, 
            "response": "M"
        }, 
        {
            "guess": "1,1\n", 
            "elapsed": 0.016035795211791992, 
            "turnnum": 53, 
            "notify": "1,1\n", 
            "starttime": 1437124408.538973, 
            "active": 0, 
            "response": "H"
        }, 
        {
            "guess": "6,7\n", 
            "elapsed": 0.02855706214904785, 
            "turnnum": 54, 
            "notify": "6,7\n", 
            "starttime": 1437124408.555016, 
            "active": 1, 
            "response": "H"
        }, 
        {
            "guess": "2,1\n", 
            "elapsed": 0.016988039016723633, 
            "turnnum": 55, 
            "notify": "2,1\n", 
            "starttime": 1437124408.583585, 
            "active": 0, 
            "response": "M"
        }, 
        {
            "guess": "5,7\n", 
            "elapsed": 0.02682018280029297, 
            "turnnum": 56, 
            "notify": "5,7\n", 
            "starttime": 1437124408.600587, 
            "active": 1, 
            "response": "M"
        }, 
        {
            "guess": "1,2\n", 
            "elapsed": 0.02218914031982422, 
            "turnnum": 57, 
            "notify": "1,2\n", 
            "starttime": 1437124408.627421, 
            "active": 0, 
            "response": "H"
        }, 
        {
            "guess": "7,7\n", 
            "elapsed": 0.022990942001342773, 
            "turnnum": 58, 
            "notify": "7,7\n", 
            "starttime": 1437124408.649621, 
            "active": 1, 
            "response": "M"
        }, 
        {
            "guess": "1,0\n", 
            "elapsed": 0.022011995315551758, 
            "turnnum": 59, 
            "notify": "1,0\n", 
            "starttime": 1437124408.672628, 
            "active": 0, 
            "response": "H"
        }, 
        {
            "guess": "6,4\n", 
            "elapsed": 0.02042698860168457, 
            "turnnum": 60, 
            "notify": "6,4\n", 
            "starttime": 1437124408.694654, 
            "active": 1, 
            "response": "H"
        }, 
        {
            "guess": "1,3\n", 
            "elapsed": 0.02078104019165039, 
            "turnnum": 61, 
            "notify": "1,3\n", 
            "starttime": 1437124408.715098, 
            "active": 0, 
            "response": "H"
        }, 
        {
            "guess": "7,4\n", 
            "elapsed": 0.023615121841430664, 
            "turnnum": 62, 
            "notify": "7,4\n", 
            "starttime": 1437124408.73589, 
            "active": 1, 
            "response": "H"
        }, 
        {
            "guess": "1,4\n", 
            "elapsed": 0.017594099044799805, 
            "turnnum": 63, 
            "notify": "1,4\n", 
            "starttime": 1437124408.759517, 
            "active": 0, 
            "response": "SA"
        }, 
        {
            "guess": "7,3\n", 
            "elapsed": 0.027886152267456055, 
            "turnnum": 64, 
            "notify": "7,3\n", 
            "starttime": 1437124408.777125, 
            "active": 1, 
            "response": "M"
        }, 
        {
            "guess": "1,5\n", 
            "elapsed": 0.01634502410888672, 
            "turnnum": 65, 
            "notify": "1,5\n", 
            "starttime": 1437124408.805029, 
            "active": 0, 
            "response": "M"
        }, 
        {
            "guess": "8,4\n", 
            "elapsed": 0.026576995849609375, 
            "turnnum": 66, 
            "notify": "8,4\n", 
            "starttime": 1437124408.821383, 
            "active": 1, 
            "response": "H"
        }, 
        {
            "guess": "8,8\n", 
            "elapsed": 0.01801896095275879, 
            "turnnum": 67, 
            "notify": "8,8\n", 
            "starttime": 1437124408.847977, 
            "active": 0, 
            "response": "M"
        }, 
        {
            "guess": "9,4\n", 
            "elapsed": 0.02440810203552246, 
            "turnnum": 68, 
            "notify": "9,4\n", 
            "starttime": 1437124408.866011, 
            "active": 1, 
            "response": "SS"
        }, 
        {
            "guess": "1,7\n", 
            "elapsed": 0.02359485626220703, 
            "turnnum": 69, 
            "notify": "1,7\n", 
            "starttime": 1437124408.890428, 
            "active": 0, 
            "response": "M"
        }, 
        {
            "guess": "9,3\n", 
            "elapsed": 0.020807981491088867, 
            "turnnum": 70, 
            "notify": "9,3\n", 
            "starttime": 1437124408.914038, 
            "active": 1, 
            "response": "M"
        }, 
        {
            "guess": "8,6\n", 
            "elapsed": 0.027373075485229492, 
            "turnnum": 71, 
            "notify": "8,6\n", 
            "starttime": 1437124408.934856, 
            "active": 0, 
            "response": "M"
        }, 
        {
            "guess": "8,3\n", 
            "elapsed": 0.015992164611816406, 
            "turnnum": 72, 
            "notify": "8,3\n", 
            "starttime": 1437124408.962246, 
            "active": 1, 
            "response": "M"
        }, 
        {
            "guess": "8,4\n", 
            "elapsed": 0.032232046127319336, 
            "turnnum": 73, 
            "notify": "8,4\n", 
            "starttime": 1437124408.978247, 
            "active": 0, 
            "response": "M"
        }, 
        {
            "guess": "8,5\n", 
            "elapsed": 0.011888980865478516, 
            "turnnum": 74, 
            "notify": "8,5\n", 
            "starttime": 1437124409.010498, 
            "active": 1, 
            "response": "M"
        }, 
        {
            "guess": "6,8\n", 
            "elapsed": 0.03977799415588379, 
            "turnnum": 75, 
            "notify": "6,8\n", 
            "starttime": 1437124409.022393, 
            "active": 0, 
            "response": "M"
        }, 
        {
            "guess": "9,5\n", 
            "elapsed": 0.004683971405029297, 
            "turnnum": 76, 
            "notify": "9,5\n", 
            "starttime": 1437124409.062182, 
            "active": 1, 
            "response": "M"
        }, 
        {
            "guess": "6,6\n", 
            "elapsed": 0.0533900260925293, 
            "turnnum": 77, 
            "notify": "6,6\n", 
            "starttime": 1437124409.066876, 
            "active": 0, 
            "response": "H"
        }, 
        {
            "guess": "5,6\n", 
            "elapsed": 0.008083105087280273, 
            "turnnum": 78, 
            "notify": "5,6\n", 
            "starttime": 1437124409.120282, 
            "active": 1, 
            "response": "M"
        }, 
        {
            "guess": "6,7\n", 
            "elapsed": 0.04256391525268555, 
            "turnnum": 79, 
            "notify": "6,7\n", 
            "starttime": 1437124409.128375, 
            "active": 0, 
            "response": "M"
        }, 
        {
            "guess": "6,8\n", 
            "elapsed": 0.005630970001220703, 
            "turnnum": 80, 
            "notify": "6,8\n", 
            "starttime": 1437124409.170954, 
            "active": 1, 
            "response": "M"
        }, 
        {
            "guess": "7,6\n", 
            "elapsed": 0.044023990631103516, 
            "turnnum": 81, 
            "notify": "7,6\n", 
            "starttime": 1437124409.176595, 
            "active": 0, 
            "response": "M"
        }, 
        {
            "guess": "6,3\n", 
            "elapsed": 0.005670070648193359, 
            "turnnum": 82, 
            "notify": "6,3\n", 
            "starttime": 1437124409.220638, 
            "active": 1, 
            "response": "SA"
        }, 
        {
            "guess": "5,6\n", 
            "elapsed": 0.0409548282623291, 
            "turnnum": 83, 
            "notify": "5,6\n", 
            "starttime": 1437124409.226314, 
            "active": 0, 
            "response": "SP"
        }, 
        {
            "guess": "5,3\n", 
            "elapsed": 0.006429910659790039, 
            "turnnum": 84, 
            "notify": "5,3\n", 
            "starttime": 1437124409.26728, 
            "active": 1, 
            "response": "M"
        }, 
        {
            "guess": "2,8\n", 
            "elapsed": 0.04296302795410156, 
            "turnnum": 85, 
            "notify": "2,8\n", 
            "starttime": 1437124409.273722, 
            "active": 0, 
            "response": "M"
        }, 
        {
            "guess": "6,2\n", 
            "elapsed": 0.0071260929107666016, 
            "turnnum": 86, 
            "notify": "6,2\n", 
            "starttime": 1437124409.316702, 
            "active": 1, 
            "response": "M"
        }, 
        {
            "guess": "4,0\n", 
            "elapsed": 0.042243003845214844, 
            "turnnum": 87, 
            "notify": "4,0\n", 
            "starttime": 1437124409.323836, 
            "active": 0, 
            "response": "M"
        }, 
        {
            "guess": "2,9\n", 
            "elapsed": 0.004957914352416992, 
            "turnnum": 88, 
            "notify": "2,9\n", 
            "starttime": 1437124409.366097, 
            "active": 1, 
            "response": "M"
        }, 
        {
            "guess": "8,2\n", 
            "elapsed": 0.03859686851501465, 
            "turnnum": 89, 
            "notify": "8,2\n", 
            "starttime": 1437124409.371067, 
            "active": 0, 
            "response": "M"
        }, 
        {
            "guess": "9,7\n", 
            "elapsed": 0.007161855697631836, 
            "turnnum": 90, 
            "notify": "9,7\n", 
            "starttime": 1437124409.409687, 
            "active": 1, 
            "response": "M"
        }, 
        {
            "guess": "3,5\n", 
            "elapsed": 0.04083395004272461, 
            "turnnum": 91, 
            "notify": "3,5\n", 
            "starttime": 1437124409.416861, 
            "active": 0, 
            "response": "M"
        }, 
        {
            "guess": "4,8\n", 
            "elapsed": 0.0043070316314697266, 
            "turnnum": 92, 
            "notify": "4,8\n", 
            "starttime": 1437124409.457706, 
            "active": 1, 
            "response": "M"
        }, 
        {
            "guess": "3,3\n", 
            "elapsed": 0.04825997352600098, 
            "turnnum": 93, 
            "notify": "3,3\n", 
            "starttime": 1437124409.462022, 
            "active": 0, 
            "response": "M"
        }, 
        {
            "guess": "0,9\n", 
            "elapsed": 0.009665966033935547, 
            "turnnum": 94, 
            "notify": "0,9\n", 
            "starttime": 1437124409.510301, 
            "active": 1, 
            "response": "M"
        }, 
        {
            "guess": "9,9\n", 
            "elapsed": 0.04091906547546387, 
            "turnnum": 95, 
            "notify": "9,9\n", 
            "starttime": 1437124409.519979, 
            "active": 0, 
            "response": "M"
        }, 
        {
            "guess": "4,9\n", 
            "elapsed": 0.005639076232910156, 
            "turnnum": 96, 
            "notify": "4,9\n", 
            "starttime": 1437124409.560909, 
            "active": 1, 
            "response": "M"
        }, 
        {
            "guess": "8,0\n", 
            "elapsed": 0.0398859977722168, 
            "turnnum": 97, 
            "notify": "8,0\n", 
            "starttime": 1437124409.566559, 
            "active": 0, 
            "response": "M"
        }, 
        {
            "guess": "0,4\n", 
            "elapsed": 0.010447025299072266, 
            "turnnum": 98, 
            "notify": "0,4\n", 
            "starttime": 1437124409.606462, 
            "active": 1, 
            "response": "M"
        }, 
        {
            "guess": "3,1\n", 
            "elapsed": 0.04251885414123535, 
            "turnnum": 99, 
            "notify": "3,1\n", 
            "starttime": 1437124409.616923, 
            "active": 0, 
            "response": "M"
        }, 
        {
            "guess": "5,8\n", 
            "elapsed": 0.006200075149536133, 
            "turnnum": 100, 
            "notify": "5,8\n", 
            "starttime": 1437124409.659457, 
            "active": 1, 
            "response": "M"
        }, 
        {
            "guess": "5,1\n", 
            "elapsed": 0.04391217231750488, 
            "turnnum": 101, 
            "notify": "5,1\n", 
            "starttime": 1437124409.66567, 
            "active": 0, 
            "response": "M"
        }, 
        {
            "guess": "7,9\n", 
            "elapsed": 0.004765987396240234, 
            "turnnum": 102, 
            "notify": "7,9\n", 
            "starttime": 1437124409.709592, 
            "active": 1, 
            "response": "M"
        }, 
        {
            "guess": "0,6\n", 
            "elapsed": 0.04069209098815918, 
            "turnnum": 103, 
            "notify": "0,6\n", 
            "starttime": 1437124409.714366, 
            "active": 0, 
            "response": "M"
        }, 
        {
            "guess": "1,0\n", 
            "elapsed": 0.009449958801269531, 
            "turnnum": 104, 
            "notify": "1,0\n", 
            "starttime": 1437124409.755071, 
            "active": 1, 
            "response": "M"
        }, 
        {
            "guess": "0,8\n", 
            "elapsed": 0.038520097732543945, 
            "turnnum": 105, 
            "notify": "0,8\n", 
            "starttime": 1437124409.764529, 
            "active": 0, 
            "response": "M"
        }, 
        {
            "guess": "4,1\n", 
            "elapsed": 0.0075609683990478516, 
            "turnnum": 106, 
            "notify": "4,1\n", 
            "starttime": 1437124409.80306, 
            "active": 1, 
            "response": "M"
        }, 
        {
            "guess": "9,7\n", 
            "elapsed": 0.040962934494018555, 
            "turnnum": 107, 
            "notify": "9,7\n", 
            "starttime": 1437124409.810632, 
            "active": 0, 
            "response": "M"
        }, 
        {
            "guess": "4,0\n", 
            "elapsed": 0.00923013687133789, 
            "turnnum": 108, 
            "notify": "4,0\n", 
            "starttime": 1437124409.851611, 
            "active": 1, 
            "response": "M"
        }, 
        {
            "guess": "9,3\n", 
            "elapsed": 0.040596961975097656, 
            "turnnum": 109, 
            "notify": "9,3\n", 
            "starttime": 1437124409.860851, 
            "active": 0, 
            "response": "M"
        }, 
        {
            "guess": "8,6\n", 
            "elapsed": 0.007715940475463867, 
            "turnnum": 110, 
            "notify": "8,6\n", 
            "starttime": 1437124409.901463, 
            "active": 1, 
            "response": "M"
        }, 
        {
            "guess": "3,9\n", 
            "elapsed": 0.04020094871520996, 
            "turnnum": 111, 
            "notify": "3,9\n", 
            "starttime": 1437124409.90919, 
            "active": 0, 
            "response": "M"
        }, 
        {
            "guess": "0,7\n", 
            "elapsed": 0.008051872253417969, 
            "turnnum": 112, 
            "notify": "0,7\n", 
            "starttime": 1437124409.949408, 
            "active": 1, 
            "response": "M"
        }, 
        {
            "guess": "7,9\n", 
            "elapsed": 0.037721872329711914, 
            "turnnum": 113, 
            "notify": "7,9\n", 
            "starttime": 1437124409.957473, 
            "active": 0, 
            "response": "M"
        }, 
        {
            "guess": "6,9\n", 
            "elapsed": 0.009624004364013672, 
            "turnnum": 114, 
            "notify": "6,9\n", 
            "starttime": 1437124409.995219, 
            "active": 1, 
            "response": "M"
        }, 
        {
            "guess": "9,5\n", 
            "elapsed": 0.03809404373168945, 
            "turnnum": 115, 
            "notify": "9,5\n", 
            "starttime": 1437124410.00485, 
            "active": 0, 
            "response": "M"
        }, 
        {
            "guess": "5,9\n", 
            "elapsed": 0.010245084762573242, 
            "turnnum": 116, 
            "notify": "5,9\n", 
            "starttime": 1437124410.04296, 
            "active": 1, 
            "response": "M"
        }, 
        {
            "guess": "5,9\n", 
            "elapsed": 0.03658890724182129, 
            "turnnum": 117, 
            "notify": "5,9\n", 
            "starttime": 1437124410.053216, 
            "active": 0, 
            "response": "M"
        }, 
        {
            "guess": "5,1\n", 
            "elapsed": 0.012275934219360352, 
            "turnnum": 118, 
            "notify": "5,1\n", 
            "starttime": 1437124410.089824, 
            "active": 1, 
            "response": "M"
        }, 
        {
            "guess": "6,0\n", 
            "elapsed": 0.03437185287475586, 
            "turnnum": 119, 
            "notify": "6,0\n", 
            "starttime": 1437124410.102112, 
            "active": 0, 
            "response": "M"
        }, 
        {
            "guess": "4,7\n", 
            "elapsed": 0.012738227844238281, 
            "turnnum": 120, 
            "notify": "4,7\n", 
            "starttime": 1437124410.1365, 
            "active": 1, 
            "response": "M"
        }, 
        {
            "guess": "0,0\n", 
            "elapsed": 0.03127622604370117, 
            "turnnum": 121, 
            "notify": "0,0\n", 
            "starttime": 1437124410.149248, 
            "active": 0, 
            "response": "M"
        }, 
        {
            "guess": "7,2\n", 
            "elapsed": 0.01034998893737793, 
            "turnnum": 122, 
            "notify": "7,2\n", 
            "starttime": 1437124410.180539, 
            "active": 1, 
            "response": "M"
        }, 
        {
            "guess": "0,4\n", 
            "elapsed": 0.03541994094848633, 
            "turnnum": 123, 
            "notify": "0,4\n", 
            "starttime": 1437124410.1909, 
            "active": 0, 
            "response": "H"
        }, 
        {
            "guess": "0,3\n", 
            "elapsed": 0.008507013320922852, 
            "turnnum": 124, 
            "notify": "0,3\n", 
            "starttime": 1437124410.226338, 
            "active": 1, 
            "response": "M"
        }, 
        {
            "guess": "0,3\n", 
            "elapsed": 0.04034304618835449, 
            "turnnum": 125, 
            "notify": "0,3\n", 
            "starttime": 1437124410.234854, 
            "active": 0, 
            "response": "H"
        }, 
        {
            "guess": "8,2\n", 
            "elapsed": 0.007850885391235352, 
            "turnnum": 126, 
            "notify": "8,2\n", 
            "starttime": 1437124410.275218, 
            "active": 1, 
            "response": "M"
        }, 
        {
            "guess": "0,2\n", 
            "elapsed": 0.0408780574798584, 
            "turnnum": 127, 
            "notify": "0,2\n", 
            "starttime": 1437124410.283077, 
            "active": 0, 
            "response": "M"
        }, 
        {
            "guess": "3,0\n", 
            "elapsed": 0.010283946990966797, 
            "turnnum": 128, 
            "notify": "3,0\n", 
            "starttime": 1437124410.32397, 
            "active": 1, 
            "response": "M"
        }, 
        {
            "guess": "0,5\n", 
            "elapsed": 0.03588700294494629, 
            "turnnum": 129, 
            "starttime": 1437124410.334268, 
            "active": 0, 
            "response": "W"
        }
    ], 
    "winner": 0, 
    "p1stdout": "", 
    "player0board": {
        "9,4": "S", 
        "8,4": "S", 
        "4,5": "D", 
        "9,1": "P", 
        "3,5": "D", 
        "7,4": "S", 
        "5,5": "D", 
        "2,3": "B", 
        "6,7": "A", 
        "2,5": "B", 
        "2,4": "B", 
        "6,3": "A", 
        "2,2": "B", 
        "6,5": "A", 
        "6,4": "A", 
        "8,1": "P", 
        "6,6": "A"
    }, 
    "player1board": {
        "0,5": "S", 
        "0,4": "S", 
        "4,7": "B", 
        "4,6": "B", 
        "4,5": "B", 
        "4,4": "B", 
        "5,6": "P", 
        "1,4": "A", 
        "1,2": "A", 
        "1,3": "A", 
        "1,0": "A", 
        "1,1": "A", 
        "0,3": "S", 
        "6,3": "D", 
        "6,2": "D", 
        "6,4": "D", 
        "6,6": "P"
    }, 
    "player0": "maxime.py", 
    "player1": "hunter.py", 
    "numturns": 129, 
    "p1stderr": "", 
    "starttime": 1437124407.026664, 
    "time": 3.343503952026367, 
    "p0stderr": "", 
    "p0stdout": ""
}