{
    "player1": "tile.py", 
    "turns": [
        {
            "guess": "4,9\n", 
            "elapsed": 0.0022280216217041016, 
            "turnnum": 1, 
            "notify": "4,9\n", 
            "starttime": 1437256630.763697, 
            "active": 0, 
            "response": "M"
        }, 
        {
            "guess": "0,0\n", 
            "elapsed": 0.003489971160888672, 
            "turnnum": 2, 
            "notify": "0,0\n", 
            "starttime": 1437256630.765933, 
            "active": 1, 
            "response": "M"
        }, 
        {
            "guess": "1,9\n", 
            "elapsed": 0.04075789451599121, 
            "turnnum": 3, 
            "notify": "1,9\n", 
            "starttime": 1437256630.769432, 
            "active": 0, 
            "response": "M"
        }, 
        {
            "guess": "1,0\n", 
            "elapsed": 0.004212141036987305, 
            "turnnum": 4, 
            "notify": "1,0\n", 
            "starttime": 1437256630.810207, 
            "active": 1, 
            "response": "M"
        }, 
        {
            "guess": "6,9\n", 
            "elapsed": 0.03904891014099121, 
            "turnnum": 5, 
            "notify": "6,9\n", 
            "starttime": 1437256630.81443, 
            "active": 0, 
            "response": "M"
        }, 
        {
            "guess": "2,0\n", 
            "elapsed": 0.006208181381225586, 
            "turnnum": 6, 
            "notify": "2,0\n", 
            "starttime": 1437256630.853499, 
            "active": 1, 
            "response": "M"
        }, 
        {
            "guess": "8,5\n", 
            "elapsed": 0.03839993476867676, 
            "turnnum": 7, 
            "notify": "8,5\n", 
            "starttime": 1437256630.859715, 
            "active": 0, 
            "response": "M"
        }, 
        {
            "guess": "3,0\n", 
            "elapsed": 0.0066890716552734375, 
            "turnnum": 8, 
            "notify": "3,0\n", 
            "starttime": 1437256630.898131, 
            "active": 1, 
            "response": "M"
        }, 
        {
            "guess": "3,2\n", 
            "elapsed": 0.03648185729980469, 
            "turnnum": 9, 
            "notify": "3,2\n", 
            "starttime": 1437256630.904834, 
            "active": 0, 
            "response": "M"
        }, 
        {
            "guess": "4,0\n", 
            "elapsed": 0.006807088851928711, 
            "turnnum": 10, 
            "notify": "4,0\n", 
            "starttime": 1437256630.941329, 
            "active": 1, 
            "response": "M"
        }, 
        {
            "guess": "7,7\n", 
            "elapsed": 0.034242868423461914, 
            "turnnum": 11, 
            "notify": "7,7\n", 
            "starttime": 1437256630.948146, 
            "active": 0, 
            "response": "H"
        }, 
        {
            "guess": "5,0\n", 
            "elapsed": 0.007704019546508789, 
            "turnnum": 12, 
            "notify": "5,0\n", 
            "starttime": 1437256630.9824, 
            "active": 1, 
            "response": "M"
        }, 
        {
            "guess": "8,3\n", 
            "elapsed": 0.03861093521118164, 
            "turnnum": 13, 
            "notify": "8,3\n", 
            "starttime": 1437256630.990111, 
            "active": 0, 
            "response": "M"
        }, 
        {
            "guess": "6,0\n", 
            "elapsed": 0.004363059997558594, 
            "turnnum": 14, 
            "notify": "6,0\n", 
            "starttime": 1437256631.028734, 
            "active": 1, 
            "response": "M"
        }, 
        {
            "guess": "1,3\n", 
            "elapsed": 0.03372502326965332, 
            "turnnum": 15, 
            "notify": "1,3\n", 
            "starttime": 1437256631.033108, 
            "active": 0, 
            "response": "H"
        }, 
        {
            "guess": "7,0\n", 
            "elapsed": 0.009492158889770508, 
            "turnnum": 16, 
            "notify": "7,0\n", 
            "starttime": 1437256631.066861, 
            "active": 1, 
            "response": "M"
        }, 
        {
            "guess": "3,8\n", 
            "elapsed": 0.03181314468383789, 
            "turnnum": 17, 
            "notify": "3,8\n", 
            "starttime": 1437256631.076372, 
            "active": 0, 
            "response": "H"
        }, 
        {
            "guess": "8,0\n", 
            "elapsed": 0.01167607307434082, 
            "turnnum": 18, 
            "notify": "8,0\n", 
            "starttime": 1437256631.108199, 
            "active": 1, 
            "response": "M"
        }, 
        {
            "guess": "9,3\n", 
            "elapsed": 0.034037113189697266, 
            "turnnum": 19, 
            "notify": "9,3\n", 
            "starttime": 1437256631.119891, 
            "active": 0, 
            "response": "M"
        }, 
        {
            "guess": "9,0\n", 
            "elapsed": 0.007073879241943359, 
            "turnnum": 20, 
            "notify": "9,0\n", 
            "starttime": 1437256631.153944, 
            "active": 1, 
            "response": "M"
        }, 
        {
            "guess": "0,0\n", 
            "elapsed": 0.03561806678771973, 
            "turnnum": 21, 
            "notify": "0,0\n", 
            "starttime": 1437256631.161025, 
            "active": 0, 
            "response": "M"
        }, 
        {
            "guess": "0,1\n", 
            "elapsed": 0.006922006607055664, 
            "turnnum": 22, 
            "notify": "0,1\n", 
            "starttime": 1437256631.196651, 
            "active": 1, 
            "response": "M"
        }, 
        {
            "guess": "8,8\n", 
            "elapsed": 0.038227081298828125, 
            "turnnum": 23, 
            "notify": "8,8\n", 
            "starttime": 1437256631.20358, 
            "active": 0, 
            "response": "M"
        }, 
        {
            "guess": "1,1\n", 
            "elapsed": 0.007389068603515625, 
            "turnnum": 24, 
            "notify": "1,1\n", 
            "starttime": 1437256631.241824, 
            "active": 1, 
            "response": "M"
        }, 
        {
            "guess": "7,9\n", 
            "elapsed": 0.03649497032165527, 
            "turnnum": 25, 
            "notify": "7,9\n", 
            "starttime": 1437256631.249226, 
            "active": 0, 
            "response": "M"
        }, 
        {
            "guess": "2,1\n", 
            "elapsed": 0.0070760250091552734, 
            "turnnum": 26, 
            "notify": "2,1\n", 
            "starttime": 1437256631.285739, 
            "active": 1, 
            "response": "H"
        }, 
        {
            "guess": "6,2\n", 
            "elapsed": 0.03635692596435547, 
            "turnnum": 27, 
            "notify": "6,2\n", 
            "starttime": 1437256631.292829, 
            "active": 0, 
            "response": "M"
        }, 
        {
            "guess": "3,1\n", 
            "elapsed": 0.007024049758911133, 
            "turnnum": 28, 
            "notify": "3,1\n", 
            "starttime": 1437256631.329198, 
            "active": 1, 
            "response": "SP"
        }, 
        {
            "guess": "5,3\n", 
            "elapsed": 0.03617286682128906, 
            "turnnum": 29, 
            "notify": "5,3\n", 
            "starttime": 1437256631.33623, 
            "active": 0, 
            "response": "M"
        }, 
        {
            "guess": "4,1\n", 
            "elapsed": 0.007951021194458008, 
            "turnnum": 30, 
            "notify": "4,1\n", 
            "starttime": 1437256631.372422, 
            "active": 1, 
            "response": "M"
        }, 
        {
            "guess": "7,1\n", 
            "elapsed": 0.0352940559387207, 
            "turnnum": 31, 
            "notify": "7,1\n", 
            "starttime": 1437256631.380384, 
            "active": 0, 
            "response": "M"
        }, 
        {
            "guess": "5,1\n", 
            "elapsed": 0.009912967681884766, 
            "turnnum": 32, 
            "notify": "5,1\n", 
            "starttime": 1437256631.415689, 
            "active": 1, 
            "response": "M"
        }, 
        {
            "guess": "4,6\n", 
            "elapsed": 0.03554391860961914, 
            "turnnum": 33, 
            "notify": "4,6\n", 
            "starttime": 1437256631.42562, 
            "active": 0, 
            "response": "M"
        }, 
        {
            "guess": "6,1\n", 
            "elapsed": 0.007570028305053711, 
            "turnnum": 34, 
            "notify": "6,1\n", 
            "starttime": 1437256631.461175, 
            "active": 1, 
            "response": "M"
        }, 
        {
            "guess": "9,0\n", 
            "elapsed": 0.03644299507141113, 
            "turnnum": 35, 
            "notify": "9,0\n", 
            "starttime": 1437256631.468754, 
            "active": 0, 
            "response": "M"
        }, 
        {
            "guess": "7,1\n", 
            "elapsed": 0.008446931838989258, 
            "turnnum": 36, 
            "notify": "7,1\n", 
            "starttime": 1437256631.505208, 
            "active": 1, 
            "response": "M"
        }, 
        {
            "guess": "6,8\n", 
            "elapsed": 0.034742116928100586, 
            "turnnum": 37, 
            "notify": "6,8\n", 
            "starttime": 1437256631.513671, 
            "active": 0, 
            "response": "M"
        }, 
        {
            "guess": "8,1\n", 
            "elapsed": 0.008162975311279297, 
            "turnnum": 38, 
            "notify": "8,1\n", 
            "starttime": 1437256631.548432, 
            "active": 1, 
            "response": "M"
        }, 
        {
            "guess": "4,3\n", 
            "elapsed": 0.0348508358001709, 
            "turnnum": 39, 
            "notify": "4,3\n", 
            "starttime": 1437256631.556605, 
            "active": 0, 
            "response": "M"
        }, 
        {
            "guess": "9,1\n", 
            "elapsed": 0.009328842163085938, 
            "turnnum": 40, 
            "notify": "9,1\n", 
            "starttime": 1437256631.591463, 
            "active": 1, 
            "response": "M"
        }, 
        {
            "guess": "2,0\n", 
            "elapsed": 0.03696608543395996, 
            "turnnum": 41, 
            "notify": "2,0\n", 
            "starttime": 1437256631.600802, 
            "active": 0, 
            "response": "M"
        }, 
        {
            "guess": "0,2\n", 
            "elapsed": 0.007135152816772461, 
            "turnnum": 42, 
            "notify": "0,2\n", 
            "starttime": 1437256631.637786, 
            "active": 1, 
            "response": "M"
        }, 
        {
            "guess": "1,6\n", 
            "elapsed": 0.0364840030670166, 
            "turnnum": 43, 
            "notify": "1,6\n", 
            "starttime": 1437256631.644929, 
            "active": 0, 
            "response": "M"
        }, 
        {
            "guess": "1,2\n", 
            "elapsed": 0.0074100494384765625, 
            "turnnum": 44, 
            "notify": "1,2\n", 
            "starttime": 1437256631.681427, 
            "active": 1, 
            "response": "H"
        }, 
        {
            "guess": "0,5\n", 
            "elapsed": 0.03707289695739746, 
            "turnnum": 45, 
            "notify": "0,5\n", 
            "starttime": 1437256631.688846, 
            "active": 0, 
            "response": "M"
        }, 
        {
            "guess": "2,2\n", 
            "elapsed": 0.0069200992584228516, 
            "turnnum": 46, 
            "notify": "2,2\n", 
            "starttime": 1437256631.725932, 
            "active": 1, 
            "response": "H"
        }, 
        {
            "guess": "4,2\n", 
            "elapsed": 0.03453207015991211, 
            "turnnum": 47, 
            "notify": "4,2\n", 
            "starttime": 1437256631.732857, 
            "active": 0, 
            "response": "H"
        }, 
        {
            "guess": "3,2\n", 
            "elapsed": 0.01105809211730957, 
            "turnnum": 48, 
            "notify": "3,2\n", 
            "starttime": 1437256631.767395, 
            "active": 1, 
            "response": "H"
        }, 
        {
            "guess": "5,1\n", 
            "elapsed": 0.034707069396972656, 
            "turnnum": 49, 
            "notify": "5,1\n", 
            "starttime": 1437256631.778473, 
            "active": 0, 
            "response": "M"
        }, 
        {
            "guess": "4,2\n", 
            "elapsed": 0.0074121952056884766, 
            "turnnum": 50, 
            "notify": "4,2\n", 
            "starttime": 1437256631.813197, 
            "active": 1, 
            "response": "SB"
        }, 
        {
            "guess": "9,5\n", 
            "elapsed": 0.03547406196594238, 
            "turnnum": 51, 
            "notify": "9,5\n", 
            "starttime": 1437256631.820616, 
            "active": 0, 
            "response": "M"
        }, 
        {
            "guess": "5,2\n", 
            "elapsed": 0.009365081787109375, 
            "turnnum": 52, 
            "notify": "5,2\n", 
            "starttime": 1437256631.856101, 
            "active": 1, 
            "response": "M"
        }, 
        {
            "guess": "4,0\n", 
            "elapsed": 0.034493207931518555, 
            "turnnum": 53, 
            "notify": "4,0\n", 
            "starttime": 1437256631.865481, 
            "active": 0, 
            "response": "M"
        }, 
        {
            "guess": "6,2\n", 
            "elapsed": 0.008055925369262695, 
            "turnnum": 54, 
            "notify": "6,2\n", 
            "starttime": 1437256631.89999, 
            "active": 1, 
            "response": "M"
        }, 
        {
            "guess": "3,1\n", 
            "elapsed": 0.03379702568054199, 
            "turnnum": 55, 
            "notify": "3,1\n", 
            "starttime": 1437256631.908061, 
            "active": 0, 
            "response": "M"
        }, 
        {
            "guess": "7,2\n", 
            "elapsed": 0.009946107864379883, 
            "turnnum": 56, 
            "notify": "7,2\n", 
            "starttime": 1437256631.941875, 
            "active": 1, 
            "response": "M"
        }, 
        {
            "guess": "8,6\n", 
            "elapsed": 0.03375601768493652, 
            "turnnum": 57, 
            "notify": "8,6\n", 
            "starttime": 1437256631.951833, 
            "active": 0, 
            "response": "M"
        }, 
        {
            "guess": "8,2\n", 
            "elapsed": 0.008059024810791016, 
            "turnnum": 58, 
            "notify": "8,2\n", 
            "starttime": 1437256631.985605, 
            "active": 1, 
            "response": "M"
        }, 
        {
            "guess": "2,1\n", 
            "elapsed": 0.03553199768066406, 
            "turnnum": 59, 
            "notify": "2,1\n", 
            "starttime": 1437256631.993678, 
            "active": 0, 
            "response": "M"
        }, 
        {
            "guess": "9,2\n", 
            "elapsed": 0.006187915802001953, 
            "turnnum": 60, 
            "notify": "9,2\n", 
            "starttime": 1437256632.029223, 
            "active": 1, 
            "response": "M"
        }, 
        {
            "guess": "0,6\n", 
            "elapsed": 0.03815507888793945, 
            "turnnum": 61, 
            "notify": "0,6\n", 
            "starttime": 1437256632.035421, 
            "active": 0, 
            "response": "M"
        }, 
        {
            "guess": "0,3\n", 
            "elapsed": 0.006849050521850586, 
            "turnnum": 62, 
            "notify": "0,3\n", 
            "starttime": 1437256632.073593, 
            "active": 1, 
            "response": "M"
        }, 
        {
            "guess": "0,1\n", 
            "elapsed": 0.03667402267456055, 
            "turnnum": 63, 
            "notify": "0,1\n", 
            "starttime": 1437256632.080457, 
            "active": 0, 
            "response": "M"
        }, 
        {
            "guess": "1,3\n", 
            "elapsed": 0.009046077728271484, 
            "turnnum": 64, 
            "notify": "1,3\n", 
            "starttime": 1437256632.117142, 
            "active": 1, 
            "response": "M"
        }, 
        {
            "guess": "9,6\n", 
            "elapsed": 0.033660888671875, 
            "turnnum": 65, 
            "notify": "9,6\n", 
            "starttime": 1437256632.126204, 
            "active": 0, 
            "response": "M"
        }, 
        {
            "guess": "2,3\n", 
            "elapsed": 0.01031804084777832, 
            "turnnum": 66, 
            "notify": "2,3\n", 
            "starttime": 1437256632.159872, 
            "active": 1, 
            "response": "M"
        }, 
        {
            "guess": "0,7\n", 
            "elapsed": 0.035028934478759766, 
            "turnnum": 67, 
            "notify": "0,7\n", 
            "starttime": 1437256632.170206, 
            "active": 0, 
            "response": "M"
        }, 
        {
            "guess": "3,3\n", 
            "elapsed": 0.008800029754638672, 
            "turnnum": 68, 
            "notify": "3,3\n", 
            "starttime": 1437256632.205246, 
            "active": 1, 
            "response": "M"
        }, 
        {
            "guess": "1,2\n", 
            "elapsed": 0.03437304496765137, 
            "turnnum": 69, 
            "notify": "1,2\n", 
            "starttime": 1437256632.214063, 
            "active": 0, 
            "response": "H"
        }, 
        {
            "guess": "4,3\n", 
            "elapsed": 0.009910106658935547, 
            "turnnum": 70, 
            "notify": "4,3\n", 
            "starttime": 1437256632.248447, 
            "active": 1, 
            "response": "M"
        }, 
        {
            "guess": "4,8\n", 
            "elapsed": 0.0334169864654541, 
            "turnnum": 71, 
            "notify": "4,8\n", 
            "starttime": 1437256632.258372, 
            "active": 0, 
            "response": "H"
        }, 
        {
            "guess": "5,3\n", 
            "elapsed": 0.009634971618652344, 
            "turnnum": 72, 
            "notify": "5,3\n", 
            "starttime": 1437256632.2918, 
            "active": 1, 
            "response": "M"
        }, 
        {
            "guess": "9,9\n", 
            "elapsed": 0.035188913345336914, 
            "turnnum": 73, 
            "notify": "9,9\n", 
            "starttime": 1437256632.30145, 
            "active": 0, 
            "response": "M"
        }, 
        {
            "guess": "6,3\n", 
            "elapsed": 0.008471012115478516, 
            "turnnum": 74, 
            "notify": "6,3\n", 
            "starttime": 1437256632.336653, 
            "active": 1, 
            "response": "M"
        }, 
        {
            "guess": "1,5\n", 
            "elapsed": 0.0362401008605957, 
            "turnnum": 75, 
            "notify": "1,5\n", 
            "starttime": 1437256632.345135, 
            "active": 0, 
            "response": "M"
        }, 
        {
            "guess": "7,3\n", 
            "elapsed": 0.008220911026000977, 
            "turnnum": 76, 
            "notify": "7,3\n", 
            "starttime": 1437256632.38139, 
            "active": 1, 
            "response": "M"
        }, 
        {
            "guess": "9,8\n", 
            "elapsed": 0.034303903579711914, 
            "turnnum": 77, 
            "notify": "9,8\n", 
            "starttime": 1437256632.389627, 
            "active": 0, 
            "response": "M"
        }, 
        {
            "guess": "8,3\n", 
            "elapsed": 0.009042978286743164, 
            "turnnum": 78, 
            "notify": "8,3\n", 
            "starttime": 1437256632.423947, 
            "active": 1, 
            "response": "M"
        }, 
        {
            "guess": "6,1\n", 
            "elapsed": 0.031147003173828125, 
            "turnnum": 79, 
            "notify": "6,1\n", 
            "starttime": 1437256632.433, 
            "active": 0, 
            "response": "M"
        }, 
        {
            "guess": "9,3\n", 
            "elapsed": 0.013371944427490234, 
            "turnnum": 80, 
            "notify": "9,3\n", 
            "starttime": 1437256632.464154, 
            "active": 1, 
            "response": "M"
        }, 
        {
            "guess": "8,9\n", 
            "elapsed": 0.03034806251525879, 
            "turnnum": 81, 
            "notify": "8,9\n", 
            "starttime": 1437256632.477542, 
            "active": 0, 
            "response": "M"
        }, 
        {
            "guess": "0,4\n", 
            "elapsed": 0.010944128036499023, 
            "turnnum": 82, 
            "notify": "0,4\n", 
            "starttime": 1437256632.507907, 
            "active": 1, 
            "response": "H"
        }, 
        {
            "guess": "7,0\n", 
            "elapsed": 0.027673006057739258, 
            "turnnum": 83, 
            "notify": "7,0\n", 
            "starttime": 1437256632.518861, 
            "active": 0, 
            "response": "M"
        }, 
        {
            "guess": "1,4\n", 
            "elapsed": 0.017880916595458984, 
            "turnnum": 84, 
            "notify": "1,4\n", 
            "starttime": 1437256632.546545, 
            "active": 1, 
            "response": "M"
        }, 
        {
            "guess": "2,2\n", 
            "elapsed": 0.027857065200805664, 
            "turnnum": 85, 
            "notify": "2,2\n", 
            "starttime": 1437256632.564435, 
            "active": 0, 
            "response": "M"
        }, 
        {
            "guess": "2,4\n", 
            "elapsed": 0.017009973526000977, 
            "turnnum": 86, 
            "notify": "2,4\n", 
            "starttime": 1437256632.592304, 
            "active": 1, 
            "response": "M"
        }, 
        {
            "guess": "0,2\n", 
            "elapsed": 0.026705026626586914, 
            "turnnum": 87, 
            "notify": "0,2\n", 
            "starttime": 1437256632.609325, 
            "active": 0, 
            "response": "M"
        }, 
        {
            "guess": "3,4\n", 
            "elapsed": 0.018054962158203125, 
            "turnnum": 88, 
            "notify": "3,4\n", 
            "starttime": 1437256632.636042, 
            "active": 1, 
            "response": "M"
        }, 
        {
            "guess": "6,4\n", 
            "elapsed": 0.02702188491821289, 
            "turnnum": 89, 
            "notify": "6,4\n", 
            "starttime": 1437256632.654108, 
            "active": 0, 
            "response": "M"
        }, 
        {
            "guess": "4,4\n", 
            "elapsed": 0.014219999313354492, 
            "turnnum": 90, 
            "notify": "4,4\n", 
            "starttime": 1437256632.681143, 
            "active": 1, 
            "response": "M"
        }, 
        {
            "guess": "8,0\n", 
            "elapsed": 0.030534029006958008, 
            "turnnum": 91, 
            "notify": "8,0\n", 
            "starttime": 1437256632.69537, 
            "active": 0, 
            "response": "M"
        }, 
        {
            "guess": "5,4\n", 
            "elapsed": 0.011629819869995117, 
            "turnnum": 92, 
            "notify": "5,4\n", 
            "starttime": 1437256632.725922, 
            "active": 1, 
            "response": "M"
        }, 
        {
            "guess": "2,8\n", 
            "elapsed": 0.03237295150756836, 
            "turnnum": 93, 
            "notify": "2,8\n", 
            "starttime": 1437256632.737567, 
            "active": 0, 
            "response": "H"
        }, 
        {
            "guess": "6,4\n", 
            "elapsed": 0.011445999145507812, 
            "turnnum": 94, 
            "notify": "6,4\n", 
            "starttime": 1437256632.769951, 
            "active": 1, 
            "response": "M"
        }, 
        {
            "guess": "9,4\n", 
            "elapsed": 0.031105995178222656, 
            "turnnum": 95, 
            "notify": "9,4\n", 
            "starttime": 1437256632.781407, 
            "active": 0, 
            "response": "M"
        }, 
        {
            "guess": "7,4\n", 
            "elapsed": 0.013108015060424805, 
            "turnnum": 96, 
            "notify": "7,4\n", 
            "starttime": 1437256632.812533, 
            "active": 1, 
            "response": "M"
        }, 
        {
            "guess": "8,4\n", 
            "elapsed": 0.031533002853393555, 
            "turnnum": 97, 
            "notify": "8,4\n", 
            "starttime": 1437256632.825656, 
            "active": 0, 
            "response": "M"
        }, 
        {
            "guess": "8,4\n", 
            "elapsed": 0.011992931365966797, 
            "turnnum": 98, 
            "notify": "8,4\n", 
            "starttime": 1437256632.857201, 
            "active": 1, 
            "response": "M"
        }, 
        {
            "guess": "3,4\n", 
            "elapsed": 0.0328519344329834, 
            "turnnum": 99, 
            "notify": "3,4\n", 
            "starttime": 1437256632.869205, 
            "active": 0, 
            "response": "M"
        }, 
        {
            "guess": "9,4\n", 
            "elapsed": 0.011054039001464844, 
            "turnnum": 100, 
            "notify": "9,4\n", 
            "starttime": 1437256632.902076, 
            "active": 1, 
            "response": "M"
        }, 
        {
            "guess": "8,1\n", 
            "elapsed": 0.03197503089904785, 
            "turnnum": 101, 
            "notify": "8,1\n", 
            "starttime": 1437256632.913141, 
            "active": 0, 
            "response": "M"
        }, 
        {
            "guess": "0,5\n", 
            "elapsed": 0.011935949325561523, 
            "turnnum": 102, 
            "notify": "0,5\n", 
            "starttime": 1437256632.945127, 
            "active": 1, 
            "response": "H"
        }, 
        {
            "guess": "4,7\n", 
            "elapsed": 0.032685041427612305, 
            "turnnum": 103, 
            "notify": "4,7\n", 
            "starttime": 1437256632.957074, 
            "active": 0, 
            "response": "M"
        }, 
        {
            "guess": "1,5\n", 
            "elapsed": 0.011590957641601562, 
            "turnnum": 104, 
            "notify": "1,5\n", 
            "starttime": 1437256632.989777, 
            "active": 1, 
            "response": "M"
        }, 
        {
            "guess": "2,3\n", 
            "elapsed": 0.03187298774719238, 
            "turnnum": 105, 
            "notify": "2,3\n", 
            "starttime": 1437256633.001379, 
            "active": 0, 
            "response": "M"
        }, 
        {
            "guess": "2,5\n", 
            "elapsed": 0.011996030807495117, 
            "turnnum": 106, 
            "notify": "2,5\n", 
            "starttime": 1437256633.033263, 
            "active": 1, 
            "response": "M"
        }, 
        {
            "guess": "3,0\n", 
            "elapsed": 0.03109908103942871, 
            "turnnum": 107, 
            "notify": "3,0\n", 
            "starttime": 1437256633.045274, 
            "active": 0, 
            "response": "M"
        }, 
        {
            "guess": "3,5\n", 
            "elapsed": 0.011935949325561523, 
            "turnnum": 108, 
            "notify": "3,5\n", 
            "starttime": 1437256633.076391, 
            "active": 1, 
            "response": "M"
        }, 
        {
            "guess": "7,6\n", 
            "elapsed": 0.03181600570678711, 
            "turnnum": 109, 
            "notify": "7,6\n", 
            "starttime": 1437256633.088338, 
            "active": 0, 
            "response": "M"
        }, 
        {
            "guess": "4,5\n", 
            "elapsed": 0.013676881790161133, 
            "turnnum": 110, 
            "notify": "4,5\n", 
            "starttime": 1437256633.12017, 
            "active": 1, 
            "response": "M"
        }, 
        {
            "guess": "0,9\n", 
            "elapsed": 0.03145313262939453, 
            "turnnum": 111, 
            "notify": "0,9\n", 
            "starttime": 1437256633.133863, 
            "active": 0, 
            "response": "M"
        }, 
        {
            "guess": "5,5\n", 
            "elapsed": 0.012260913848876953, 
            "turnnum": 112, 
            "notify": "5,5\n", 
            "starttime": 1437256633.165332, 
            "active": 1, 
            "response": "M"
        }, 
        {
            "guess": "5,6\n", 
            "elapsed": 0.03049492835998535, 
            "turnnum": 113, 
            "notify": "5,6\n", 
            "starttime": 1437256633.177608, 
            "active": 0, 
            "response": "M"
        }, 
        {
            "guess": "6,5\n", 
            "elapsed": 0.013450145721435547, 
            "turnnum": 114, 
            "notify": "6,5\n", 
            "starttime": 1437256633.208119, 
            "active": 1, 
            "response": "M"
        }, 
        {
            "guess": "6,5\n", 
            "elapsed": 0.031616926193237305, 
            "turnnum": 115, 
            "notify": "6,5\n", 
            "starttime": 1437256633.221584, 
            "active": 0, 
            "response": "M"
        }, 
        {
            "guess": "7,5\n", 
            "elapsed": 0.012373924255371094, 
            "turnnum": 116, 
            "notify": "7,5\n", 
            "starttime": 1437256633.253212, 
            "active": 1, 
            "response": "M"
        }, 
        {
            "guess": "0,8\n", 
            "elapsed": 0.030114173889160156, 
            "turnnum": 117, 
            "notify": "0,8\n", 
            "starttime": 1437256633.265601, 
            "active": 0, 
            "response": "H"
        }, 
        {
            "guess": "8,5\n", 
            "elapsed": 0.012002944946289062, 
            "turnnum": 118, 
            "notify": "8,5\n", 
            "starttime": 1437256633.295725, 
            "active": 1, 
            "response": "M"
        }, 
        {
            "guess": "2,6\n", 
            "elapsed": 0.03351092338562012, 
            "turnnum": 119, 
            "notify": "2,6\n", 
            "starttime": 1437256633.307738, 
            "active": 0, 
            "response": "H"
        }, 
        {
            "guess": "9,5\n", 
            "elapsed": 0.014240026473999023, 
            "turnnum": 120, 
            "notify": "9,5\n", 
            "starttime": 1437256633.341265, 
            "active": 1, 
            "response": "M"
        }, 
        {
            "guess": "0,3\n", 
            "elapsed": 0.029419898986816406, 
            "turnnum": 121, 
            "notify": "0,3\n", 
            "starttime": 1437256633.355514, 
            "active": 0, 
            "response": "M"
        }, 
        {
            "guess": "0,6\n", 
            "elapsed": 0.012532949447631836, 
            "turnnum": 122, 
            "notify": "0,6\n", 
            "starttime": 1437256633.384946, 
            "active": 1, 
            "response": "SD"
        }, 
        {
            "guess": "9,1\n", 
            "elapsed": 0.03197312355041504, 
            "turnnum": 123, 
            "notify": "9,1\n", 
            "starttime": 1437256633.397493, 
            "active": 0, 
            "response": "M"
        }, 
        {
            "guess": "1,6\n", 
            "elapsed": 0.010013103485107422, 
            "turnnum": 124, 
            "notify": "1,6\n", 
            "starttime": 1437256633.429482, 
            "active": 1, 
            "response": "M"
        }, 
        {
            "guess": "1,4\n", 
            "elapsed": 0.032438039779663086, 
            "turnnum": 125, 
            "notify": "1,4\n", 
            "starttime": 1437256633.439504, 
            "active": 0, 
            "response": "H"
        }, 
        {
            "guess": "2,6\n", 
            "elapsed": 0.009467124938964844, 
            "turnnum": 126, 
            "notify": "2,6\n", 
            "starttime": 1437256633.471953, 
            "active": 1, 
            "response": "M"
        }, 
        {
            "guess": "1,1\n", 
            "elapsed": 0.03609204292297363, 
            "turnnum": 127, 
            "notify": "1,1\n", 
            "starttime": 1437256633.481435, 
            "active": 0, 
            "response": "SB"
        }, 
        {
            "guess": "3,6\n", 
            "elapsed": 0.007379055023193359, 
            "turnnum": 128, 
            "notify": "3,6\n", 
            "starttime": 1437256633.517544, 
            "active": 1, 
            "response": "M"
        }, 
        {
            "guess": "3,6\n", 
            "elapsed": 0.03380703926086426, 
            "turnnum": 129, 
            "notify": "3,6\n", 
            "starttime": 1437256633.524934, 
            "active": 0, 
            "response": "M"
        }, 
        {
            "guess": "4,6\n", 
            "elapsed": 0.00947713851928711, 
            "turnnum": 130, 
            "notify": "4,6\n", 
            "starttime": 1437256633.55875, 
            "active": 1, 
            "response": "M"
        }, 
        {
            "guess": "6,3\n", 
            "elapsed": 0.032958984375, 
            "turnnum": 131, 
            "notify": "6,3\n", 
            "starttime": 1437256633.568239, 
            "active": 0, 
            "response": "M"
        }, 
        {
            "guess": "5,6\n", 
            "elapsed": 0.011815786361694336, 
            "turnnum": 132, 
            "notify": "5,6\n", 
            "starttime": 1437256633.60121, 
            "active": 1, 
            "response": "M"
        }, 
        {
            "guess": "5,0\n", 
            "elapsed": 0.032624006271362305, 
            "turnnum": 133, 
            "notify": "5,0\n", 
            "starttime": 1437256633.613037, 
            "active": 0, 
            "response": "M"
        }, 
        {
            "guess": "6,6\n", 
            "elapsed": 0.011771202087402344, 
            "turnnum": 134, 
            "notify": "6,6\n", 
            "starttime": 1437256633.645676, 
            "active": 1, 
            "response": "M"
        }, 
        {
            "guess": "3,5\n", 
            "elapsed": 0.03197002410888672, 
            "turnnum": 135, 
            "notify": "3,5\n", 
            "starttime": 1437256633.657461, 
            "active": 0, 
            "response": "M"
        }, 
        {
            "guess": "7,6\n", 
            "elapsed": 0.010197162628173828, 
            "turnnum": 136, 
            "notify": "7,6\n", 
            "starttime": 1437256633.689447, 
            "active": 1, 
            "response": "M"
        }, 
        {
            "guess": "6,0\n", 
            "elapsed": 0.03371787071228027, 
            "turnnum": 137, 
            "notify": "6,0\n", 
            "starttime": 1437256633.699654, 
            "active": 0, 
            "response": "M"
        }, 
        {
            "guess": "8,6\n", 
            "elapsed": 0.012053966522216797, 
            "turnnum": 138, 
            "notify": "8,6\n", 
            "starttime": 1437256633.733383, 
            "active": 1, 
            "response": "M"
        }, 
        {
            "guess": "7,4\n", 
            "elapsed": 0.03257012367248535, 
            "turnnum": 139, 
            "notify": "7,4\n", 
            "starttime": 1437256633.745452, 
            "active": 0, 
            "response": "M"
        }, 
        {
            "guess": "9,6\n", 
            "elapsed": 0.01085209846496582, 
            "turnnum": 140, 
            "notify": "9,6\n", 
            "starttime": 1437256633.778033, 
            "active": 1, 
            "response": "M"
        }, 
        {
            "guess": "6,7\n", 
            "elapsed": 0.032655954360961914, 
            "turnnum": 141, 
            "notify": "6,7\n", 
            "starttime": 1437256633.788894, 
            "active": 0, 
            "response": "H"
        }, 
        {
            "guess": "0,7\n", 
            "elapsed": 0.012021064758300781, 
            "turnnum": 142, 
            "notify": "0,7\n", 
            "starttime": 1437256633.821565, 
            "active": 1, 
            "response": "M"
        }, 
        {
            "guess": "1,0\n", 
            "elapsed": 0.03157210350036621, 
            "turnnum": 143, 
            "notify": "1,0\n", 
            "starttime": 1437256633.833601, 
            "active": 0, 
            "response": "M"
        }, 
        {
            "guess": "1,7\n", 
            "elapsed": 0.011946916580200195, 
            "turnnum": 144, 
            "notify": "1,7\n", 
            "starttime": 1437256633.865185, 
            "active": 1, 
            "response": "M"
        }, 
        {
            "guess": "2,4\n", 
            "elapsed": 0.03438901901245117, 
            "turnnum": 145, 
            "notify": "2,4\n", 
            "starttime": 1437256633.877142, 
            "active": 0, 
            "response": "H"
        }, 
        {
            "guess": "2,7\n", 
            "elapsed": 0.016243934631347656, 
            "turnnum": 146, 
            "notify": "2,7\n", 
            "starttime": 1437256633.91154, 
            "active": 1, 
            "response": "M"
        }, 
        {
            "guess": "5,4\n", 
            "elapsed": 0.02640509605407715, 
            "turnnum": 147, 
            "notify": "5,4\n", 
            "starttime": 1437256633.927794, 
            "active": 0, 
            "response": "M"
        }, 
        {
            "guess": "3,7\n", 
            "elapsed": 0.016057968139648438, 
            "turnnum": 148, 
            "notify": "3,7\n", 
            "starttime": 1437256633.954209, 
            "active": 1, 
            "response": "M"
        }, 
        {
            "guess": "4,1\n", 
            "elapsed": 0.02620387077331543, 
            "turnnum": 149, 
            "notify": "4,1\n", 
            "starttime": 1437256633.970277, 
            "active": 0, 
            "response": "M"
        }, 
        {
            "guess": "4,7\n", 
            "elapsed": 0.013993024826049805, 
            "turnnum": 150, 
            "notify": "4,7\n", 
            "starttime": 1437256633.996491, 
            "active": 1, 
            "response": "M"
        }, 
        {
            "guess": "4,4\n", 
            "elapsed": 0.03054499626159668, 
            "turnnum": 151, 
            "notify": "4,4\n", 
            "starttime": 1437256634.010494, 
            "active": 0, 
            "response": "M"
        }, 
        {
            "guess": "5,7\n", 
            "elapsed": 0.009912967681884766, 
            "turnnum": 152, 
            "notify": "5,7\n", 
            "starttime": 1437256634.041049, 
            "active": 1, 
            "response": "M"
        }, 
        {
            "guess": "3,9\n", 
            "elapsed": 0.035140037536621094, 
            "turnnum": 153, 
            "notify": "3,9\n", 
            "starttime": 1437256634.050972, 
            "active": 0, 
            "response": "M"
        }, 
        {
            "guess": "6,7\n", 
            "elapsed": 0.004405975341796875, 
            "turnnum": 154, 
            "notify": "6,7\n", 
            "starttime": 1437256634.086128, 
            "active": 1, 
            "response": "M"
        }, 
        {
            "guess": "7,5\n", 
            "elapsed": 0.03597903251647949, 
            "turnnum": 155, 
            "notify": "7,5\n", 
            "starttime": 1437256634.090543, 
            "active": 0, 
            "response": "M"
        }, 
        {
            "guess": "7,7\n", 
            "elapsed": 0.010696172714233398, 
            "turnnum": 156, 
            "notify": "7,7\n", 
            "starttime": 1437256634.126531, 
            "active": 1, 
            "response": "M"
        }, 
        {
            "guess": "0,4\n", 
            "elapsed": 0.03082418441772461, 
            "turnnum": 157, 
            "notify": "0,4\n", 
            "starttime": 1437256634.137235, 
            "active": 0, 
            "response": "M"
        }, 
        {
            "guess": "8,7\n", 
            "elapsed": 0.011976003646850586, 
            "turnnum": 158, 
            "notify": "8,7\n", 
            "starttime": 1437256634.168066, 
            "active": 1, 
            "response": "M"
        }, 
        {
            "guess": "2,7\n", 
            "elapsed": 0.029881954193115234, 
            "turnnum": 159, 
            "notify": "2,7\n", 
            "starttime": 1437256634.180054, 
            "active": 0, 
            "response": "M"
        }, 
        {
            "guess": "9,7\n", 
            "elapsed": 0.018331050872802734, 
            "turnnum": 160, 
            "notify": "9,7\n", 
            "starttime": 1437256634.209941, 
            "active": 1, 
            "response": "M"
        }, 
        {
            "guess": "5,7\n", 
            "elapsed": 0.025831937789916992, 
            "turnnum": 161, 
            "notify": "5,7\n", 
            "starttime": 1437256634.228287, 
            "active": 0, 
            "response": "M"
        }, 
        {
            "guess": "0,8\n", 
            "elapsed": 0.017332077026367188, 
            "turnnum": 162, 
            "notify": "0,8\n", 
            "starttime": 1437256634.254135, 
            "active": 1, 
            "response": "M"
        }, 
        {
            "guess": "2,9\n", 
            "elapsed": 0.024899005889892578, 
            "turnnum": 163, 
            "notify": "2,9\n", 
            "starttime": 1437256634.271474, 
            "active": 0, 
            "response": "M"
        }, 
        {
            "guess": "1,8\n", 
            "elapsed": 0.024753808975219727, 
            "turnnum": 164, 
            "notify": "1,8\n", 
            "starttime": 1437256634.296389, 
            "active": 1, 
            "response": "M"
        }, 
        {
            "guess": "5,5\n", 
            "elapsed": 0.020110130310058594, 
            "turnnum": 165, 
            "notify": "5,5\n", 
            "starttime": 1437256634.321153, 
            "active": 0, 
            "response": "M"
        }, 
        {
            "guess": "2,8\n", 
            "elapsed": 0.023524045944213867, 
            "turnnum": 166, 
            "notify": "2,8\n", 
            "starttime": 1437256634.341274, 
            "active": 1, 
            "response": "H"
        }, 
        {
            "guess": "8,7\n", 
            "elapsed": 0.02172088623046875, 
            "turnnum": 167, 
            "notify": "8,7\n", 
            "starttime": 1437256634.364808, 
            "active": 0, 
            "response": "SD"
        }, 
        {
            "guess": "3,8\n", 
            "elapsed": 0.02037191390991211, 
            "turnnum": 168, 
            "notify": "3,8\n", 
            "starttime": 1437256634.386542, 
            "active": 1, 
            "response": "H"
        }, 
        {
            "guess": "5,9\n", 
            "elapsed": 0.020915985107421875, 
            "turnnum": 169, 
            "notify": "5,9\n", 
            "starttime": 1437256634.406927, 
            "active": 0, 
            "response": "M"
        }, 
        {
            "guess": "4,8\n", 
            "elapsed": 0.021336078643798828, 
            "turnnum": 170, 
            "notify": "4,8\n", 
            "starttime": 1437256634.427855, 
            "active": 1, 
            "response": "H"
        }, 
        {
            "guess": "2,5\n", 
            "elapsed": 0.024688005447387695, 
            "turnnum": 171, 
            "notify": "2,5\n", 
            "starttime": 1437256634.449205, 
            "active": 0, 
            "response": "SS"
        }, 
        {
            "guess": "5,8\n", 
            "elapsed": 0.01888298988342285, 
            "turnnum": 172, 
            "notify": "5,8\n", 
            "starttime": 1437256634.473908, 
            "active": 1, 
            "response": "H"
        }, 
        {
            "guess": "1,8\n", 
            "elapsed": 0.024916887283325195, 
            "turnnum": 173, 
            "notify": "1,8\n", 
            "starttime": 1437256634.4928, 
            "active": 0, 
            "response": "SA"
        }, 
        {
            "guess": "6,8\n", 
            "elapsed": 0.01918506622314453, 
            "turnnum": 174, 
            "notify": "6,8\n", 
            "starttime": 1437256634.517732, 
            "active": 1, 
            "response": "SA"
        }, 
        {
            "guess": "5,8\n", 
            "elapsed": 0.026546955108642578, 
            "turnnum": 175, 
            "notify": "5,8\n", 
            "starttime": 1437256634.536937, 
            "active": 0, 
            "response": "M"
        }, 
        {
            "guess": "7,8\n", 
            "elapsed": 0.018590927124023438, 
            "turnnum": 176, 
            "notify": "7,8\n", 
            "starttime": 1437256634.563496, 
            "active": 1, 
            "response": "M"
        }, 
        {
            "guess": "9,7\n", 
            "elapsed": 0.022175073623657227, 
            "turnnum": 177, 
            "notify": "9,7\n", 
            "starttime": 1437256634.582104, 
            "active": 0, 
            "response": "M"
        }, 
        {
            "guess": "8,8\n", 
            "elapsed": 0.02174687385559082, 
            "turnnum": 178, 
            "notify": "8,8\n", 
            "starttime": 1437256634.60429, 
            "active": 1, 
            "response": "M"
        }, 
        {
            "guess": "9,2\n", 
            "elapsed": 0.021734952926635742, 
            "turnnum": 179, 
            "notify": "9,2\n", 
            "starttime": 1437256634.626053, 
            "active": 0, 
            "response": "M"
        }, 
        {
            "guess": "9,8\n", 
            "elapsed": 0.022542953491210938, 
            "turnnum": 180, 
            "notify": "9,8\n", 
            "starttime": 1437256634.647804, 
            "active": 1, 
            "response": "M"
        }, 
        {
            "guess": "7,3\n", 
            "elapsed": 0.017312049865722656, 
            "turnnum": 181, 
            "notify": "7,3\n", 
            "starttime": 1437256634.670362, 
            "active": 0, 
            "response": "M"
        }, 
        {
            "guess": "0,9\n", 
            "elapsed": 0.025389909744262695, 
            "turnnum": 182, 
            "notify": "0,9\n", 
            "starttime": 1437256634.687684, 
            "active": 1, 
            "response": "M"
        }, 
        {
            "guess": "3,3\n", 
            "elapsed": 0.020162105560302734, 
            "turnnum": 183, 
            "notify": "3,3\n", 
            "starttime": 1437256634.713084, 
            "active": 0, 
            "response": "M"
        }, 
        {
            "guess": "1,9\n", 
            "elapsed": 0.023097991943359375, 
            "turnnum": 184, 
            "notify": "1,9\n", 
            "starttime": 1437256634.733262, 
            "active": 1, 
            "response": "M"
        }, 
        {
            "guess": "6,6\n", 
            "elapsed": 0.022378921508789062, 
            "turnnum": 185, 
            "notify": "6,6\n", 
            "starttime": 1437256634.756367, 
            "active": 0, 
            "response": "M"
        }, 
        {
            "guess": "2,9\n", 
            "elapsed": 0.02070307731628418, 
            "turnnum": 186, 
            "notify": "2,9\n", 
            "starttime": 1437256634.778765, 
            "active": 1, 
            "response": "M"
        }, 
        {
            "guess": "5,2\n", 
            "elapsed": 0.020104169845581055, 
            "turnnum": 187, 
            "starttime": 1437256634.799476, 
            "active": 0, 
            "response": "W"
        }
    ], 
    "winner": 0, 
    "p1stdout": "", 
    "player1board": {
        "4,2": "P", 
        "3,8": "A", 
        "1,8": "A", 
        "5,2": "P", 
        "1,1": "B", 
        "1,4": "B", 
        "4,8": "A", 
        "1,2": "B", 
        "1,3": "B", 
        "7,7": "D", 
        "0,8": "A", 
        "2,5": "S", 
        "2,8": "A", 
        "8,7": "D", 
        "2,4": "S", 
        "2,6": "S", 
        "6,7": "D"
    }, 
    "player0": "randguess.py", 
    "player0board": {
        "0,6": "D", 
        "0,5": "D", 
        "0,4": "D", 
        "3,8": "A", 
        "4,2": "B", 
        "4,8": "A", 
        "1,2": "B", 
        "3,1": "P", 
        "3,2": "B", 
        "6,9": "S", 
        "6,8": "A", 
        "7,9": "S", 
        "5,8": "A", 
        "2,8": "A", 
        "8,9": "S", 
        "2,1": "P", 
        "2,2": "B"
    }, 
    "numturns": 187, 
    "p1stderr": "", 
    "starttime": 1437256630.642352, 
    "time": 4.177239894866943, 
    "p0stderr": "", 
    "id": 333, 
    "p0stdout": ""
}